LICENSE.txt
MANIFEST.in
README.rst
proof.png
setup.py
main/__init__.py
time_converters.egg-info/PKG-INFO
time_converters.egg-info/SOURCES.txt
time_converters.egg-info/dependency_links.txt
time_converters.egg-info/top_level.txt