Metadata-Version: 2.1
Name: time-converters
Version: 1.6.9
Summary: Converts e.g. 24h to 86400
Home-page: https://skayus.pl/
Author: Skayuś
Author-email: skayuus@gmail.com
License: MIT
Keywords: time convert hour second
Platform: UNKNOWN
Classifier: Development Status :: 5 - Production/Stable
Classifier: Intended Audience :: Education
Classifier: Operating System :: Microsoft :: Windows :: Windows 10
Classifier: License :: OSI Approved :: MIT License
Classifier: Programming Language :: Python :: 3
License-File: LICENSE.txt
